{
  "$schema": "https://developer.microsoft.com/json-schemas/fabric/item/report/definition/visualContainer/2.6.0/schema.json",
  "name": "20b4c0610e0418909a68",
  "position": {
    "x": 10,
    "y": 0,
    "z": 0,
    "height": 280,
    "width": 280,
    "tabOrder": 0
  },
  "visual": {
    "visualType": "waterfallChart",
    "query": {
      "queryState": {
        "Category": {
          "projections": [
            {
              "field": {
                "Column": {
                  "Expression": {
                    "SourceRef": {
                      "Entity": "DateTable"
                    }
                  },
                  "Property": "MonthYear"
                }
              },
              "queryRef": "DateTable.MonthYear",
              "nativeQueryRef": "MonthYear",
              "active": true
            }
          ]
        },
        "Y": {
          "projections": [
            {
              "field": {
                "Measure": {
                  "Expression": {
                    "SourceRef": {
                      "Entity": "CostExports"
                    }
                  },
                  "Property": "Cost MoM Change"
                }
              },
              "queryRef": "CostExports.Cost MoM Change",
              "nativeQueryRef": "Cost MoM Change"
            }
          ]
        }
      },
      "sortDefinition": {
        "sort": [
          {
            "field": {
              "Measure": {
                "Expression": {
                  "SourceRef": {
                    "Entity": "CostExports"
                  }
                },
                "Property": "Cost MoM Change"
              }
            },
            "direction": "Descending"
          }
        ],
        "isDefaultSort": true
      }
    },
    "drillFilterOtherVisuals": true
  }
}