{
  "$schema": "https://developer.microsoft.com/json-schemas/fabric/item/report/definition/visualContainer/2.6.0/schema.json",
  "name": "4496fc17ac68a2639873",
  "position": {
    "x": 821.78539224526594,
    "y": 0,
    "z": 2,
    "height": 188.13345356176734,
    "width": 357.79981965734896,
    "tabOrder": 2
  },
  "visual": {
    "visualType": "cardVisual",
    "query": {
      "queryState": {
        "Data": {
          "projections": [
            {
              "field": {
                "Measure": {
                  "Expression": {
                    "SourceRef": {
                      "Entity": "CostExports"
                    }
                  },
                  "Property": "Cost MoM %"
                }
              },
              "queryRef": "CostExports.Cost MoM %",
              "nativeQueryRef": "Cost MoM %"
            }
          ]
        }
      },
      "sortDefinition": {
        "sort": [
          {
            "field": {
              "Measure": {
                "Expression": {
                  "SourceRef": {
                    "Entity": "CostExports"
                  }
                },
                "Property": "Cost MoM %"
              }
            },
            "direction": "Descending"
          }
        ],
        "isDefaultSort": true
      }
    },
    "drillFilterOtherVisuals": true
  }
}